[
  {
    "name": "Galaxy S23 Ultra",
    "brand": "Samsung",
    "price": 1199.99,
    "category": "Smartphone",
    "image": "https://example.com/images/galaxy-s23-ultra.jpg",
    "ram": "12GB",
    "rom": "256GB",
    "camera": "200MP + 12MP + 10MP + 10MP",
    "screen_size": "6.8 inches",
    "battery": "5000mAh",
    "processor": "Snapdragon 8 Gen 2",
    "colour": "Phantom Black"
  },
  {
    "name": "iPhone 15 Pro Max",
    "brand": "Apple",
    "price": 1299.99,
    "category": "Smartphone",
    "image": "https://example.com/images/iphone-15-pro-max.jpg",
    "ram": "8GB",
    "rom": "512GB",
    "camera": "48MP + 12MP + 12MP",
    "screen_size": "6.7 inches",
    "battery": "4422mAh",
    "processor": "A17 Pro",
    "colour": "Natural Titanium"
  },
  {
    "name": "OnePlus 12",
    "brand": "OnePlus",
    "price": 799.00,
    "category": "Smartphone",
    "image": "https://example.com/images/oneplus-12.jpg",
    "ram": "12GB",
    "rom": "256GB",
    "camera": "50MP + 48MP + 64MP",
    "screen_size": "6.82 inches",
    "battery": "5400mAh",
    "processor": "Snapdragon 8 Gen 3",
    "colour": "Flowy Emerald"
  },
  {
    "name": "Pixel 8 Pro",
    "brand": "Google",
    "price": 999.00,
    "category": "Smartphone",
    "image": "https://example.com/images/pixel-8-pro.jpg",
    "ram": "12GB",
    "rom": "128GB",
    "camera": "50MP + 48MP + 48MP",
    "screen_size": "6.7 ",
    "battery": "5050mAh",
    "processor": "Google Tensor G3",
    "colour": "Obsidiainchesn"
  },
  {
    "name": "Xiaomi 14 Pro",
    "brand": "Xiaomi",
    "price": 699.99,
    "category": "Smartphone",
    "image": "https://example.com/images/xiaomi-14-pro.jpg",
    "ram": "12GB",
    "rom": "256GB",
    "camera": "50MP + 50MP + 50MP",
    "screen_size": "6.73 inches",
    "battery": "4880mAh",
    "processor": "Snapdragon 8 Gen 3",
    "colour": "Black"
  },
  {
    "name": "Motorola Edge 40 Pro",
    "brand": "Motorola",
    "price": 799.99,
    "category": "Smartphone",
    "image": "https://example.com/images/edge-40-pro.jpg",
    "ram": "12GB",
    "rom": "256GB",
    "camera": "50MP + 50MP + 12MP",
    "screen_size": "6.67 inches",
    "battery": "4600mAh",
    "processor": "Snapdragon 8 Gen 2",
    "colour": "Lunar Blue"
  },
  {
    "name": "Asus ROG Phone 7",
    "brand": "Asus",
    "price": 999.00,
    "category": "Smartphone",
    "image": "https://example.com/images/rog-phone-7.jpg",
    "ram": "16GB",
    "rom": "512GB",
    "camera": "50MP + 13MP + 5MP",
    "screen_size": "6.78 inches",
    "battery": "6000mAh",
    "processor": "Snapdragon 8 Gen 2",
    "colour": "Storm White"
  },
  {
    "name": "Realme GT 5",
    "brand": "Realme",
    "price": 649.99,
    "category": "Smartphone",
    "image": "https://example.com/images/realme-gt5.jpg",
    "ram": "16GB",
    "rom": "512GB",
    "camera": "50MP + 8MP + 2MP",
    "screen_size": "6.74 inches",
    "battery": "5240mAh",
    "processor": "Snapdragon 8 Gen 2",
    "colour": "Flowing Silver"
  },
  {
    "name": "iQOO Neo 10R 5G",
    "brand": "iQOO",
    "price": 1399.00,
    "category": "Smartphone",
    "image": "https://example.com/images/xperia-1-v.jpg",
    "ram": "8GB",
    "rom": "256GB",
    "camera": "50MP + 8MP + 32MP",
    "screen_size": "6.78 inches",
    "battery": "6400mAh",
    "processor": "Snapdragon 8s Gen 3",
    "colour": "Moonknight Titanium"
  },
  {
    "name": "Vivo X100 Pro",
    "brand": "Vivo",
    "price": 899.99,
    "category": "Smartphone",
    "image": "https://example.com/images/vivo-x100-pro.jpg",
    "ram": "16GB",
    "rom": "512GB",
    "camera": "50MP + 50MP + 64MP",
    "screen_size": "6.78 inches",
    "battery": "5400mAh",
    "processor": "Dimensity 9300",
    "colour": "Asteroid Black"
  },
  {
    "name": "iQOO 13 5G",
    "brand": "iQOO",
    "price": 749.00,
    "category": "Smartphone",
    "image": "https://example.com/images/iqoo-13-5g.jpg",
    "ram": "12GB",
    "rom": "512GB",
    "camera": "50MP + 50MP + 64MP",
    "screen_size": "6.78 inches",
    "battery": "5000mAh",
    "processor": "Snapdragon 8 Gen 3",
    "colour": "Legend White"
  },
  {
    "name": "Infinix Zero 30",
    "brand": "Infinix",
    "price": 299.99,
    "category": "Smartphone",
    "image": "https://example.com/images/infinix-zero-30.jpg",
    "ram": "12GB",
    "rom": "256GB",
    "camera": "108MP + 13MP + 2MP",
    "screen_size": "6.78 inches",
    "battery": "5000mAh",
    "processor": "MediaTek Dimensity 8020",
    "colour": "Golden Hour"
  },
  {
    "name": "Lava Agni 2",
    "brand": "Lava",
    "price": 249.99,
    "category": "Smartphone",
    "image": "https://example.com/images/lava-agni-2.jpg",
    "ram": "8GB",
    "rom": "128GB",
    "camera": "50MP Quad Camera",
    "screen_size": "6.5 inches",
    "battery": "4700mAh",
    "processor": "MediaTek Dimensity 7050",
    "colour": "Viridian"
  },
  {
    "name": "Nothing Phone (2)",
    "brand": "Nothing",
    "price": 599.00,
    "category": "Smartphone",
    "image": "https://example.com/images/nothing-phone-2.jpg",
    "ram": "12GB",
    "rom": "256GB",
    "camera": "50MP + 50MP",
    "screen_size": "6.7 inches",
    "battery": "4700mAh",
    "processor": "Snapdragon 8+ Gen 1",
    "colour": "Dark Grey"
  },
  {
    "name": "Samsung Galaxy A54",
    "brand": "Samsung",
    "price": 449.00,
    "category": "Smartphone",
    "image": "https://example.com/images/galaxy-a54.jpg",
    "ram": "8GB",
    "rom": "128GB",
    "camera": "50MP + 12MP + 5MP",
    "screen_size": "6.4 inches",
    "battery": "5000mAh",
    "processor": "Exynos 1380",
    "colour": "Awesome Lime"
  },
  {
    "name": "Poco F5 Pro",
    "brand": "Poco",
    "price": 479.00,
    "category": "Smartphone",
    "image": "https://example.com/images/poco-f5-pro.jpg",
    "ram": "12GB",
    "rom": "256GB",
    "camera": "64MP + 8MP + 2MP",
    "screen_size": "6.67 inches",
    "battery": "5160mAh",
    "processor": "Snapdragon 8+ Gen 1",
    "colour": "Carbon Black"
  },
  {
    "name": "Tecno Phantom V Flip",
    "brand": "Tecno",
    "price": 699.00,
    "category": "Smartphone",
    "image": "https://example.com/images/phantom-v-flip.jpg",
    "ram": "8GB",
    "rom": "256GB",
    "camera": "64MP + 13MP",
    "screen_size": "6.9 inches",
    "battery": "4000mAh",
    "processor": "Dimensity 8050",
    "colour": "Mystic Dawn"
  },
  {
    "name": "Honor Magic5 Pro",
    "brand": "Honor",
    "price": 1099.00,
    "category": "Smartphone",
    "image": "https://example.com/images/honor-magic5-pro.jpg",
    "ram": "12GB",
    "rom": "512GB",
    "camera": "50MP + 50MP + 50MP",
    "screen_size": "6.81 inches",
    "battery": "5100mAh",
    "processor": "Snapdragon 8 Gen 2",
    "colour": "Meadow Green"
  },
  {
    "name": "Lava Storm Play 5G",
    "brand": "Lava",
    "price": 499.00,
    "category": "Smartphone",
    "image": "https://example.com/images/lava-storm-play-5g.jpg",
    "ram": "8GB",
    "rom": "256GB",
    "camera": "50 MP AI Camera",
    "screen_size": "6.75 inches HD+ Display",
    "battery": "5000mAh",
    "processor": "India's First MT D7060 Processor with 525k Antutu ",
    "colour": "Frosty Blue"
  },
  {
    "name": "Lava Bold N1 Pro",
    "brand": "Lava",
    "price": 699.00,
    "category": "Smartphone",
    "image": "https://example.com/images/lava-bold-n1-pro.jpg",
    "ram": "4 GB",
    "rom": "128 GB",
    "camera": "50 MP AI Triple Rear Camera | 8 MP Front Camera",
    "screen_size": "Bigger 6.67 inches HD+ IP54 Display",
    "battery": "5000mAh",
    "processor": "Snapdragon 8 Gen 2",
    "colour": "Titanium Gold 4 GB "
  }
]
